sos_bioinfo/__init__.py
sos_bioinfo/__init__.py.bak
sos_bioinfo/_version.py
sos_bioinfo/_version.py.bak
sos_bioinfo/preview.py
sos_bioinfo/preview.py.bak
sos_bioinfo-0.17.4.dist-info/METADATA
sos_bioinfo-0.17.4.dist-info/RECORD
sos_bioinfo-0.17.4.dist-info/WHEEL
sos_bioinfo-0.17.4.dist-info/entry_points.txt
sos_bioinfo-0.17.4.dist-info/top_level.txt
