Metadata-Version: 2.1
Name: sos-bioinfo
Version: 0.17.4
Summary: SoS Notebook extension for bioinformatics applications
Home-page: https://github.com/vatlab/SOS
Author: Bo Peng
Author-email: bpeng@mdanderson.org
Maintainer: Bo Peng
Maintainer-email: bpeng@mdanderson.org
License: 3-clause BSD
Platform: UNKNOWN
Classifier: Development Status :: 4 - Beta
Classifier: Environment :: Console
Classifier: License :: OSI Approved :: GNU General Public License (GPL)
Classifier: Natural Language :: English
Classifier: Operating System :: POSIX :: Linux
Classifier: Operating System :: MacOS :: MacOS X
Classifier: Operating System :: Microsoft :: Windows
Classifier: Intended Audience :: Information Technology
Classifier: Intended Audience :: Science/Research
Classifier: Programming Language :: Python :: 3 :: Only
Classifier: Programming Language :: Python :: Implementation :: CPython
Provides-Extra: sam
Requires-Dist: sos (>=0.17.4)
Provides-Extra: sam
Requires-Dist: pysam; extra == 'sam'
